check_online_presence.py
web_accounts_list_checker.py
whatsmyname/__init__.py
whatsmyname/main.py
whatsmyname/app/__init__.py
whatsmyname/app/config.py
whatsmyname/app/cli/__init__.py
whatsmyname/app/cli/args.py
whatsmyname/app/extractors/__init__.py
whatsmyname/app/extractors/file_extractors.py
whatsmyname/app/models/__init__.py
whatsmyname/app/models/enums/__init__.py
whatsmyname/app/models/enums/common.py
whatsmyname/app/models/schemas/__init__.py
whatsmyname/app/models/schemas/cli.py
whatsmyname/app/models/schemas/sites.py
whatsmyname/app/tasks/__init__.py
whatsmyname/app/tasks/process.py
whatsmyname/app/utilities/__init__.py
whatsmyname/app/utilities/formatters.py
what_is_my_name-0.0.5.dist-info/METADATA
what_is_my_name-0.0.5.dist-info/WHEEL
what_is_my_name-0.0.5.dist-info/licenses/LICENSE.md
what_is_my_name-0.0.5.dist-info/RECORD
