Metadata-Version: 2.1
Name: what-is-my-name
Version: 0.0.5
Summary: Enumerate over a list of websites and check for registered users by username.
Project-URL: Homepage, https://github.com/WebBreacher/WhatsMyName
Project-URL: Bug Tracker, https://github.com/WebBreacher/WhatsMyName/issues
Author-email: Micah Hoffman <author@example.com>, Dan Cardin <dcardin2007@gmail.com>
License: Copyright (C) 2022 Micah Hoffman, Dan Cardin
Classifier: Programming Language :: Python :: 3
Requires-Python: >=3.8
